[{"line":1,"elements":[{"start_timestamp":"2023-11-09T19:57:08.207Z","line":19,"name":"Register user on HotelWeb","description":"","id":"register-hotelweb-account;register-user-on-hotelweb;;2","type":"scenario","keyword":"Scenario Outline","steps":[{"result":{"duration":2165702100,"status":"passed"},"line":5,"name":"Page 'https://hotel-testlab.coderslab.pl/en/' opened in browser","match":{"arguments":[{"val":"'https://hotel-testlab.coderslab.pl/en/'","offset":5}],"location":"hotelweb.HotelRegisterSteps.pageOpen(java.lang.String)"},"keyword":"Given "},{"result":{"duration":238741500,"status":"passed"},"line":7,"name":"Button SignIn clicked","match":{"location":"hotelweb.HotelRegisterSteps.buttonSignInClicked()"},"keyword":"When "},{"result":{"duration":60054300,"status":"passed"},"line":8,"name":"Email filled and ENTER pushed","match":{"location":"hotelweb.HotelRegisterSteps.emailFilled()"},"keyword":"And "},{"result":{"duration":949215900,"status":"passed"},"line":9,"name":"form filled with Arek,Krzyk,erjuiwshjrfuiwj","match":{"arguments":[{"val":"Arek","offset":17},{"val":"Krzyk","offset":22},{"val":"erjuiwshjrfuiwj","offset":28}],"location":"hotelweb.HotelRegisterSteps.formFilled(java.lang.String,java.lang.String,java.lang.String)"},"keyword":"And "},{"result":{"duration":325511600,"status":"passed"},"line":11,"name":"Button Register clicked","match":{"location":"hotelweb.HotelRegisterSteps.buttonRegisterClicked()"},"keyword":"And "},{"result":{"duration":17015500,"status":"passed"},"line":13,"name":"Check if account created","match":{"location":"hotelweb.HotelRegisterSteps.checkIfAccountCreated()"},"keyword":"Then "},{"result":{"duration":185860700,"status":"passed"},"line":14,"name":"Save screenshot","match":{"location":"hotelweb.HotelRegisterSteps.saveScreenshot()"},"keyword":"And "},{"result":{"duration":1001400,"status":"passed"},"line":15,"name":"Close browser","match":{"location":"hotelweb.HotelRegisterSteps.closeBrowser()"},"keyword":"And "}]},{"start_timestamp":"2023-11-09T19:57:12.185Z","line":20,"name":"Register user on HotelWeb","description":"","id":"register-hotelweb-account;register-user-on-hotelweb;;3","type":"scenario","keyword":"Scenario Outline","steps":[{"result":{"duration":1562524300,"status":"passed"},"line":5,"name":"Page 'https://hotel-testlab.coderslab.pl/en/' opened in browser","match":{"arguments":[{"val":"'https://hotel-testlab.coderslab.pl/en/'","offset":5}],"location":"hotelweb.HotelRegisterSteps.pageOpen(java.lang.String)"},"keyword":"Given "},{"result":{"duration":218313600,"status":"passed"},"line":7,"name":"Button SignIn clicked","match":{"location":"hotelweb.HotelRegisterSteps.buttonSignInClicked()"},"keyword":"When "},{"result":{"duration":54049400,"status":"passed"},"line":8,"name":"Email filled and ENTER pushed","match":{"location":"hotelweb.HotelRegisterSteps.emailFilled()"},"keyword":"And "},{"result":{"duration":938332700,"status":"passed"},"line":9,"name":"form filled with Janusz,Kowalski,rwr3rsfse","match":{"arguments":[{"val":"Janusz","offset":17},{"val":"Kowalski","offset":24},{"val":"rwr3rsfse","offset":33}],"location":"hotelweb.HotelRegisterSteps.formFilled(java.lang.String,java.lang.String,java.lang.String)"},"keyword":"And "},{"result":{"duration":316691600,"status":"passed"},"line":11,"name":"Button Register clicked","match":{"location":"hotelweb.HotelRegisterSteps.buttonRegisterClicked()"},"keyword":"And "},{"result":{"duration":15014200,"status":"passed"},"line":13,"name":"Check if account created","match":{"location":"hotelweb.HotelRegisterSteps.checkIfAccountCreated()"},"keyword":"Then "},{"result":{"duration":183371500,"status":"passed"},"line":14,"name":"Save screenshot","match":{"location":"hotelweb.HotelRegisterSteps.saveScreenshot()"},"keyword":"And "},{"result":{"duration":1001100,"status":"passed"},"line":15,"name":"Close browser","match":{"location":"hotelweb.HotelRegisterSteps.closeBrowser()"},"keyword":"And "}]}],"name":"Register HotelWeb Account","description":"","id":"register-hotelweb-account","keyword":"Feature","uri":"file:src/test/resources/features/HotelCucu.feature","tags":[]}]